pypomes_http/__init__.py
pypomes_http/http_async.py
pypomes_http/http_methods.py
pypomes_http/http_pomes.py
pypomes_http/http_statuses.py
pypomes_http-0.8.2.dist-info/METADATA
pypomes_http-0.8.2.dist-info/WHEEL
pypomes_http-0.8.2.dist-info/licenses/LICENSE
pypomes_http-0.8.2.dist-info/RECORD
